{ 
   "colors": { 
      "button_background_active": "#244270",
      "button_background_hover":"#244270",
      "icons_attention": "#B2C0CC",
      "frame":"#0c1634",
      "ntp_background":"#0c1634",
      "ntp_text":"#B2C0CC",
      "tab_background_text":"#B2C0CC",
      "tab_line":"#B2C0CC",
      "tab_loading":"#B2C0CC",
      "tab_selected":"#244270",
      "tab_text":"#B2C0CC",
      "toolbar":"#0c1634",
      "toolbar_field":"#449ACD",
      "toolbar_field_highlight":"#0c1634",
      "toolbar_field_highlight_text":"#B2C0CC",
      "toolbar_field_separator":"#B2C0CC",
      "toolbar_field_text":"#1B539B",
      "toolbar_field_text_focus":"#1B539B",
      "toolbar_text":"#B2C0CC",
      "popup":"#0c1634",
      "popup_highlight": "#B2C0CC",	
      "popup_border":"#0c1634",
      "popup_highlight_text": "#244270",
      "popup_text":"#B2C0CC",
      "sidebar":"#0c1634",
      "sidebar_border":"#0c1634",
      "sidebar_highlight":"#B2C0CC",
      "sidebar_highlight_text":"#0c1634",
      "sidebar_text":"#B2C0CC"
    }
}
